alfa_orders/__init__.py
alfa_orders/api.py
alfa_orders/columns.py
alfa_orders/config.py
alfa_orders/loaders/__init__.py
alfa_orders/loaders/base.py
alfa_orders/loaders/refunds.py
alfa_orders/loaders/transactions.py
alfa_orders/models.py
alfa_orders/processors.py
alfa_orders/session.py
alfa_orders/utils.py
alfa_orders-0.4.0.dist-info/WHEEL
alfa_orders-0.4.0.dist-info/METADATA
alfa_orders-0.4.0.dist-info/RECORD
