Metadata-Version: 2.1
Name: alfa-orders
Version: 0.4.0
Summary: Lib for loading AlfaBank orders
Author: potykion
Author-email: potykion@gmail.com
Requires-Python: >=3.7,<4.0
Classifier: Programming Language :: Python :: 3
Classifier: Programming Language :: Python :: 3.7
Classifier: Programming Language :: Python :: 3.8
Requires-Dist: more-itertools (>=7.2,<8.0)
Requires-Dist: requests (>=2.22,<3.0)
Requires-Dist: toolz (>=0.10.0,<0.11.0)
Requires-Dist: typing-extensions (>=3.7,<4.0)
